[{"obl": true, "code": "1TE705", "name": "Introduktion till elektroteknik", "level": "G1N", "period": "11", "credits": "5"},
{"obl": true, "code": "1TE704", "name": "Elektroteknikens grunder I: ", "level": "G1N", "period": "11", "credits": "5"},
{"obl": true, "code": "1MA008", "name": "Algebra och vektorgeometri", "level": "G1N", "period": "11", "credits": "5"},
{"obl": true, "code": "1MA013", "name": "Envariabelanalys", "level": "G1F", "period": "12", "credits": "(5)"},
{"obl": true, "code": "1TE667", "name": "Elektroteknikens grunder II: ", "level": "G1F", "period": "12", "credits": "5"},
{"obl": true, "code": "1TE668", "name": null, "level": null, "period": "12", "credits": null},
{"obl": false, "code": "1TN000", "name": "Studieteknik", "level": "G1N", "period": "12", "credits": "1"},
{"obl": true, "code": "1MA013", "name": null, "level": null, "period": "12", "credits": "(5)10"},
{"obl": true, "code": "1TE668", "name": "Projektarbete i elektroteknik", "level": "G1F", "period": "12", "credits": "(10) 15"},
{"obl": true, "code": "1TE669", "name": "Elektroteknikens grunder III: ", "level": "G1F", "period": "14", "credits": "10"},
{"obl": true, "code": "1FA518", "name": "Mekanik HI", "level": "G1F", "period": "14", "credits": "5"},
{"obl": true, "code": "1TE646", "name": "Elektronik", "level": "G1F", "period": "21", "credits": "(10)"},
{"obl": true, "code": "1MA034", "name": "Transformmetoder", "level": "G1F", "period": "21", "credits": "5"},
{"obl": true, "code": "1TE646", "name": "Elektronik, del 2", "level": "G1F", "period": "22", "credits": "(10) 20"},
{"obl": true, "code": "1TD393", "name": "Ber\u00e4kningsvetenskap I", "level": "G1F", "period": "22", "credits": "5"},
{"obl": true, "code": "1TE655", "name": "Elkraftteknik", "level": "G2F", "period": "23", "credits": "5"},
{"obl": true, "code": "1TE670", "name": "Roterande elektriska maskiner", "level": "G2F", "period": "23", "credits": "5"},
{"obl": true, "code": "1MS008", "name": "Statistik f\u00f6r ingenj\u00f6rer", "level": "G1F", "period": "23", "credits": "5"},
{"obl": true, "code": "1TE671", "name": "Elektriska transmissionssystem", "level": "G2F", "period": "24", "credits": "10"},
{"obl": true, "code": "1TE649", "name": "CAD med FEM", "level": "G1F", "period": "24", "credits": "5"},
{"obl": true, "code": "1TE672", "name": "M\u00e4t- och styrsystem", "level": "G2F", "period": "31", "credits": "(5)"},
{"obl": true, "code": "1TD433", "name": "Programmeringsteknik I", "level": "G1N", "period": "31", "credits": "5"},
{"obl": false, "code": "1TE061", "name": "Industriell projektledning", "level": "G1F", "period": "31", "credits": "5"},
{"obl": true, "code": "1TE672", "name": "M\u00e4t- och styrsystem", "level": "G2F", "period": "32", "credits": "(10)"},
{"obl": true, "code": "2FE025", "name": "F\u00f6retagsekonomi, baskurs A/B", "level": "G1N", "period": "32", "credits": "5"},
{"obl": true, "code": "1TE672", "name": "M\u00e4t- och styrsystem", "level": "G2F", "period": "33", "credits": "(5) 20"},
{"obl": false, "code": "1TE063", "name": "Kundfokuserad produktutveckling", "level": "A1N", "period": "33", "credits": "5"},
{"obl": false, "code": "5EN361", "name": "Engelska f\u00f6r ingenj\u00f6rer", "level": "G1F", "period": "33", "credits": "5"},
{"obl": false, "code": "1FA326", "name": "Digital elektronikkonstruktion med VHDL", "level": "A1N", "period": "33", "credits": "10"},
{"obl": false, "code": "1TE615", "name": "Projektarbete i elektricitetsl\u00e4ra", "level": "A1N", "period": "33", "credits": "5"},
{"obl": false, "code": "1TE616", "name": "Projektarbete i elektricitetsl\u00e4ra", "level": "A1N", "period": "33", "credits": "10"},
{"obl": true, "code": "1TE660", "name": "Examensarbete i elektroteknik", "level": "G2E", "period": "34", "credits": "15"}]