[{"credits": "10", "level": "G1N", "code": "1DT051", "period": "11", "name": "Introduktion till informationsteknologi"},
{"credits": "5", "level": "G1N", "code": "1MA010", "period": "11", "name": "Baskurs i matematik"},
{"credits": "(10)", "level": "G1F", "code": "1DL201", "period": "12", "name": "Programkonstruktion och datastrukturer"},
{"credits": "5", "level": "G1F", "code": "1MA004", "period": "12", "name": "Algebra I"},
{"credits": "(10) 20", "level": "G1F", "code": "1DL201", "period": "13", "name": "Programkonstruktion och datastrukturer"},
{"credits": "(5)", "level": "G1F", "code": "1MA013", "period": "13", "name": "Envariabelanalys"},
{"credits": "10", "level": "G1F", "code": "1DT093", "period": "14", "name": "Datorarkitektur "},
{"credits": "(5) 10", "level": "G1F", "code": "1MA013", "period": "14", "name": "Envariabelanalys"},
{"credits": "(10)", "level": "G1F", "code": "1DL221", "period": "21", "name": "Imperativ och objektorienterad programmeringsmetodik"},
{"credits": "5", "level": "G1F", "code": "1MA025", "period": "21", "name": "Linj\u00e4r algebra och geometri I"},
{"credits": "5", "level": "G1F", "code": "1DL500", "period": "22", "name": "Automater och logik i modellering av IT-system"},
{"credits": "(10) 20", "level": "G1F", "code": "1DL221", "period": "22", "name": "Imperativ och objektorienterad programmeringsmetodik"},
{"credits": "5", "level": "G1N", "code": "1MD016", "period": "23", "name": "M\u00e4nniska-datorinteraktion"},
{"credits": "5", "level": "G1F", "code": "1MA024", "period": "23", "name": "Linj\u00e4r algebra II"},
{"credits": "5", "level": "G1F", "code": "1DT044", "period": "23", "name": "Operativsystem I"},
{"credits": "5", "level": "G1F", "code": "1MS005", "period": "24", "name": "Sannolikhet och statistik"},
{"credits": "10", "level": "G1F", "code": "1TE717", "period": "24", "name": "Digitalteknik och elektronik"},
{"credits": "5", "level": "G1F", "code": "1DT052", "period": "31", "name": "Datakommunikation I"},
{"credits": "5", "level": "G1F", "code": "1TD394", "period": "31", "name": "Ber\u00e4kningsvetenskap"},
{"credits": "5", "level": "G1F", "code": "1MA034", "period": "31", "name": "Transformmetoder"},
{"credits": "(5)", "level": "G2F", "code": "1TE682", "period": "32", "name": "Signaler och inbyggda system"},
{"credits": "(5)10", "level": "G2F", "code": "1TE682", "period": "33", "name": "Signaler och inbyggda system"},
{"credits": "5", "level": "G1N", "code": "1MD016", "period": "33", "name": "M\u00e4nniska-datorinteraktion"},
{"credits": "5", "level": "G1F", "code": "1DL300", "period": "33", "name": "Databasteknik I"},
{"credits": "15", "level": "G2E", "code": "1DT350", "period": "34", "name": "Sj\u00e4lvst\u00e4ndigt arbete i informationsteknologi"},
{"credits": "5", "level": "G2F", "code": "1DT002", "period": "34", "name": "Uppsatsmetodik"},
{"credits": "5", "level": "G1F", "code": "1RT155", "period": "34", "name": "Modellelering av dynamiska system "},
{"credits": "10", "level": "A1N", "code": "1DT092", "period": "34", "name": "Internationell mjukvaruutveckling, projekt"}]